igannotator/__init__.py
igannotator/annotations.py
igannotator/atomic_sentences.py
igannotator/backend.py
igannotator/frontend.py
igannotator/ig_script.py
igannotator/sentence_type.py
igannotator/sentence_type_classifier.joblib
igannotator/annotator/__init__.py
igannotator/annotator/annotator.py
igannotator/annotator/ig_annotator.py
igannotator/annotator/lexical_tree.py
igannotator/annotator/stanford_annotator.py
igannotator/output/__init__.py
igannotator/output/tsv.py
igannotator/rulesexecutor/__init__.py
igannotator/rulesexecutor/ig_element.py
igannotator/rulesexecutor/rules.py
igannotator/rulesexecutor/rules_english_constitutive.py
igannotator/rulesexecutor/rules_english_regulative.py
igannotator/rulesexecutor/rules_executor.py
igannotator-1.3.2.dist-info/LICENSE
igannotator-1.3.2.dist-info/METADATA
igannotator-1.3.2.dist-info/WHEEL
igannotator-1.3.2.dist-info/entry_points.txt
igannotator-1.3.2.dist-info/top_level.txt
igannotator-1.3.2.dist-info/RECORD
