Metadata-Version: 2.1
Name: igannotator
Version: 1.3.2
Summary: Sentence annotation with Institutional Grammar 2.0 syntax with natural language processing for document analysis
Home-page: 
Author: Aleksandra Wichrowska, Karol Saputa
Author-email: 
License: MIT
Platform: UNKNOWN
Classifier: Development Status :: 5 - Production/Stable
Classifier: License :: OSI Approved :: MIT License
Classifier: Programming Language :: Python
Classifier: Programming Language :: Python :: 3.6
Classifier: Programming Language :: Python :: 3.7
Classifier: Programming Language :: Python :: 3.8
Classifier: Programming Language :: Python :: 3.9
License-File: LICENSE
Requires-Dist: stanza (==1.2.2)
Requires-Dist: pandas (>=1.1&<=1.3.9)
Requires-Dist: spacy (==3.1.1)
Requires-Dist: joblib (==1.0.1)
Requires-Dist: scikit-learn (==0.23.1)
